rtl/core/v60_defines.sv
`ifndef V60_DEFINES_SV
`define V60_DEFINES_SV

// V60 Architecture Constants
`define V60_DATA_WIDTH      32
`define V60_ADDR_WIDTH      32
`define V60_REG_WIDTH       32
`define V60_NUM_REGS        32

// General Purpose Registers (R0-R31)
`define V60_REG_R0          5'd0
`define V60_REG_R1          5'd1
`define V60_REG_R2          5'd2
`define V60_REG_R3          5'd3
`define V60_REG_R4          5'd4
`define V60_REG_R5          5'd5
`define V60_REG_R6          5'd6
`define V60_REG_R7          5'd7
`define V60_REG_R8          5'd8
`define V60_REG_R9          5'd9
`define V60_REG_R10         5'd10
`define V60_REG_R11         5'd11
`define V60_REG_R12         5'd12
`define V60_REG_R13         5'd13
`define V60_REG_R14         5'd14
`define V60_REG_R15         5'd15
`define V60_REG_R16         5'd16
`define V60_REG_R17         5'd17
`define V60_REG_R18         5'd18
`define V60_REG_R19         5'd19
`define V60_REG_R20         5'd20
`define V60_REG_R21         5'd21
`define V60_REG_R22         5'd22
`define V60_REG_R23         5'd23
`define V60_REG_R24         5'd24
`define V60_REG_R25         5'd25
`define V60_REG_R26         5'd26
`define V60_REG_R27         5'd27
`define V60_REG_R28         5'd28
`define V60_REG_R29         5'd29
`define V60_REG_R30         5'd30
`define V60_REG_R31         5'd31

// Special Purpose Registers (implicitly selected by instructions)
`define V60_REG_AP          5'd29   // Argument Pointer (R29)
`define V60_REG_FP          5'd30   // Frame Pointer (R30)
`define V60_REG_SP          5'd31   // Stack Pointer (R31)

// Program Status Word (PSW) bits
`define V60_PSW_V           0   // Overflow
`define V60_PSW_C           1   // Carry
`define V60_PSW_Z           2   // Zero
`define V60_PSW_S           3   // Sign
`define V60_PSW_TB          4   // Trap on Branch
`define V60_PSW_TP          5   // Trap Pending
`define V60_PSW_FPT         6   // Floating Point Trap
`define V60_PSW_PRNG        9:7 // Privilege Ring (0-7)
`define V60_PSW_IS          10  // Interrupt State
`define V60_PSW_FUD         11  // FPU Disable
`define V60_PSW_AT          12  // Address Translation
`define V60_PSW_DB          13  // Debug
`define V60_PSW_IM          14  // Interrupt Mask
`define V60_PSW_I           15  // Interrupt Enable

// Instruction Format Types (from V60 manual)
`define V60_FMT_I           3'd0   // Format I: One-byte instructions
`define V60_FMT_II          3'd1   // Format II: Two-byte instructions
`define V60_FMT_III         3'd2   // Format III: Instructions with immediate
`define V60_FMT_IV          3'd3   // Format IV: Instructions with displacement
`define V60_FMT_V           3'd4   // Format V: Two-operand instructions
`define V60_FMT_VI          3'd5   // Format VI: Three-operand instructions
`define V60_FMT_VII         3'd6   // Format VII: Special format instructions
`define V60_FMT_RESERVED    3'd7   // Reserved format

// Data Types
`define V60_TYPE_BYTE       2'd0   // 8-bit
`define V60_TYPE_HALFWORD   2'd1   // 16-bit
`define V60_TYPE_WORD       2'd2   // 32-bit
`define V60_TYPE_EXTENDED   2'd3   // 64-bit (FPU)

// Addressing Modes
`define V60_AM_REGISTER     3'd0   // Register direct
`define V60_AM_IMMEDIATE    3'd1   // Immediate
`define V60_AM_MEMORY       3'd2   // Memory direct
`define V60_AM_INDEXED      3'd3   // Register indirect with index
`define V60_AM_AUTOINCR     3'd4   // Auto-increment
`define V60_AM_AUTODECR     3'd5   // Auto-decrement
`define V60_AM_DISPLACED    3'd6   // Register indirect with displacement
`define V60_AM_PCRELATIVE   3'd7   // PC-relative

// Memory Access Types
`define V60_MEM_IDLE        2'd0
`define V60_MEM_READ        2'd1
`define V60_MEM_WRITE       2'd2
`define V60_MEM_RMW         2'd3   // Read-Modify-Write

// Exception Vectors
`define V60_VEC_RESET       8'h00
`define V60_VEC_NMI         8'h01
`define V60_VEC_INVALID_OP  8'h06
`define V60_VEC_DIV_ZERO    8'h07
`define V60_VEC_OVERFLOW    8'h08
`define V60_VEC_BOUNDS      8'h09
`define V60_VEC_DEBUG       8'h0D
`define V60_VEC_PAGE_FAULT  8'h0E
`define V60_VEC_ALIGNMENT   8'h11

`endif // V60_DEFINES_SV

rtl/core/v60_decoder.sv
`include "v60_defines.sv"

module v60_decoder (
    input  logic [47:0]  inst,           // 6-byte instruction buffer
    input  logic         valid,          // Input valid signal
    
    output logic [7:0]   opcode,         // Decoded opcode
    output logic [2:0]   format,         // Instruction format
    output logic [1:0]   data_type,      // Data type (byte/halfword/word)
    output logic [4:0]   src_reg,        // Source register
    output logic [4:0]   dst_reg,        // Destination register
    output logic [31:0]  immediate,      // Immediate value
    output logic [2:0]   inst_length,    // Instruction length in bytes
    output logic         uses_memory,    // Instruction uses memory
    output logic         illegal         // Illegal instruction
);

    // Internal signals
    logic [7:0]  opcode_byte;
    logic [2:0]  addr_mode_src;
    logic [2:0]  addr_mode_dst;
    logic        has_modrm;
    logic        has_sib;
    logic [1:0]  displacement_size;
    logic [1:0]  immediate_size;
    
    // Extract first opcode byte
    assign opcode_byte = inst[47:40];
    
    // Decode main opcode groups
    always_comb begin
        // Default values
        opcode = opcode_byte;
        format = `V60_FMT_I;
        data_type = `V60_TYPE_WORD;
        src_reg = 5'h0;
        dst_reg = 5'h0;
        immediate = 32'h0;
        inst_length = 3'd1;
        uses_memory = 1'b0;
        illegal = 1'b0;
        has_modrm = 1'b0;
        has_sib = 1'b0;
        displacement_size = 2'd0;
        immediate_size = 2'd0;
        
        if (!valid) begin
            illegal = 1'b1;
        end else begin
            // Decode based on opcode patterns
            casez (opcode_byte)
                // MOV instructions
                8'b1000_10??: begin  // MOV r/m, r (88-8B)
                    format = `V60_FMT_V;
                    data_type = opcode_byte[0] ? `V60_TYPE_WORD : `V60_TYPE_BYTE;
                    has_modrm = 1'b1;
                    uses_memory = 1'b1;
                end
                
                8'b1000_11??: begin  // MOV r, r/m (8A-8D)
                    format = `V60_FMT_V;
                    data_type = opcode_byte[0] ? `V60_TYPE_WORD : `V60_TYPE_BYTE;
                    has_modrm = 1'b1;
                    uses_memory = 1'b1;
                end
                
                8'b1011_????: begin  // MOV r, imm (B0-BF)
                    format = `V60_FMT_III;
                    dst_reg = {1'b0, opcode_byte[3:0]}; // Extend to 5 bits
                    data_type = opcode_byte[3] ? `V60_TYPE_WORD : `V60_TYPE_BYTE;
                    immediate_size = opcode_byte[3] ? 2'd2 : 2'd0; // 4 bytes or 1 byte
                    inst_length = opcode_byte[3] ? 3'd5 : 3'd2;
                end
                
                // ALU instructions
                8'b0000_00??: begin  // ADD r/m, r
                    format = `V60_FMT_V;
                    data_type = opcode_byte[0] ? `V60_TYPE_WORD : `V60_TYPE_BYTE;
                    has_modrm = 1'b1;
                end
                
                8'b0000_10??: begin  // ADD r, r/m
                    format = `V60_FMT_V;
                    data_type = opcode_byte[0] ? `V60_TYPE_WORD : `V60_TYPE_BYTE;
                    has_modrm = 1'b1;
                end
                
                8'b0010_10??: begin  // SUB r/m, r
                    format = `V60_FMT_V;
                    data_type = opcode_byte[0] ? `V60_TYPE_WORD : `V60_TYPE_BYTE;
                    has_modrm = 1'b1;
                end
                
                // Jump/Branch instructions
                8'b1110_1011: begin  // JMP rel8
                    format = `V60_FMT_III;
                    immediate_size = 2'd0; // 1 byte
                    inst_length = 3'd2;
                end
                
                8'b1110_1001: begin  // JMP rel32
                    format = `V60_FMT_III;
                    immediate_size = 2'd2; // 4 bytes
                    inst_length = 3'd5;
                end
                
                8'b0111_????: begin  // Jcc rel8 (conditional jumps)
                    format = `V60_FMT_III;
                    immediate_size = 2'd0; // 1 byte
                    inst_length = 3'd2;
                end
                
                // Stack operations
                8'b0101_0???: begin  // PUSH r
                    format = `V60_FMT_II;
                    src_reg = {2'b00, opcode_byte[2:0]}; // Extend to 5 bits
                    uses_memory = 1'b1;
                end
                
                8'b0101_1???: begin  // POP r
                    format = `V60_FMT_II;
                    dst_reg = {2'b00, opcode_byte[2:0]}; // Extend to 5 bits
                    uses_memory = 1'b1;
                end
                
                // NOP
                8'b1001_0000: begin  // NOP
                    format = `V60_FMT_I;
                    inst_length = 3'd1;
                end
                
                // HALT
                8'b1111_0100: begin  // HLT
                    format = `V60_FMT_I;
                    inst_length = 3'd1;
                end
                
                default: begin
                    illegal = 1'b1;
                end
            endcase
            
            // Handle ModR/M byte decoding
            if (has_modrm && inst_length == 3'd1) begin
                logic [7:0] modrm = inst[39:32];
                logic [1:0] mod_field = modrm[7:6];
                logic [2:0] reg_field = modrm[5:3];
                logic [2:0] rm_field = modrm[2:0];
                
                inst_length = 3'd2; // At least 2 bytes with ModR/M
                
                // Decode addressing mode
                case (mod_field)
                    2'b00: begin // No displacement (except special cases)
                        if (rm_field == 3'b101) begin
                            displacement_size = 2'd2; // 32-bit displacement
                            inst_length = 3'd6;
                        end else if (rm_field == 3'b100) begin
                            has_sib = 1'b1;
                            inst_length = 3'd3;
                        end
                    end
                    2'b01: begin // 8-bit displacement
                        displacement_size = 2'd0;
                        inst_length = has_sib ? 3'd4 : 3'd3;
                    end
                    2'b10: begin // 32-bit displacement
                        displacement_size = 2'd2;
                        inst_length = has_sib ? 3'd7 : 3'd6;
                    end
                    2'b11: begin // Register direct
                        uses_memory = 1'b0;
                        src_reg = rm_field;
                        dst_reg = reg_field;
                    end
                endcase
            end
            
            // Extract immediate value
            case (immediate_size)
                2'd0: immediate = {{24{inst[31]}}, inst[31:24]}; // Sign-extend 8-bit
                2'd1: immediate = {{16{inst[23]}}, inst[23:8]};  // Sign-extend 16-bit
                2'd2: immediate = inst[15:0];                     // 32-bit
                default: immediate = 32'h0;
            endcase
        end
    end

endmodule

tb/v60_decoder_tb.sv
`timescale 1ns/1ps
`include "v60_defines.sv"

module v60_decoder_tb;

    // Decoder signals
    logic [47:0] inst;           // 6-byte instruction buffer
    logic        valid;          // Input valid signal
    
    logic [7:0]  opcode;         // Decoded opcode
    logic [2:0]  format;         // Instruction format
    logic [1:0]  data_type;      // Data type (byte/halfword/word)
    logic [4:0]  src_reg;        // Source register
    logic [4:0]  dst_reg;        // Destination register
    logic [31:0] immediate;      // Immediate value
    logic [2:0]  inst_length;    // Instruction length in bytes
    logic        uses_memory;    // Instruction uses memory
    logic        illegal;        // Illegal instruction
    
    // DUT instantiation
    v60_decoder dut (
        .inst        (inst),
        .valid       (valid),
        .opcode      (opcode),
        .format      (format),
        .data_type   (data_type),
        .src_reg     (src_reg),
        .dst_reg     (dst_reg),
        .immediate   (immediate),
        .inst_length (inst_length),
        .uses_memory (uses_memory),
        .illegal     (illegal)
    );
    
    // Helper task to display instruction decode results
    task display_decode(input string test_name, input [47:0] test_inst);
        inst = test_inst;
        valid = 1'b1;
        #1; // Allow combinational delay
        
        $display("\n--- %s ---", test_name);
        $display("Instruction: 0x%012x", test_inst);
        $display("Opcode: 0x%02x", opcode);
        $display("Format: %s", format == `V60_FMT_I ? "I" :
                              format == `V60_FMT_II ? "II" :
                              format == `V60_FMT_III ? "III" :
                              format == `V60_FMT_IV ? "IV" :
                              format == `V60_FMT_V ? "V" :
                              format == `V60_FMT_VI ? "VI" :
                              format == `V60_FMT_VII ? "VII" : "RESERVED");
        $display("Data Type: %s", data_type == `V60_TYPE_BYTE ? "BYTE" :
                                 data_type == `V60_TYPE_HALFWORD ? "HALFWORD" :
                                 data_type == `V60_TYPE_WORD ? "WORD" : "EXTENDED");
        $display("Src Reg: R%0d, Dst Reg: R%0d", src_reg, dst_reg);
        $display("Immediate: 0x%08x", immediate);
        $display("Length: %0d bytes", inst_length);
        $display("Uses Memory: %b", uses_memory);
        $display("Illegal: %b", illegal);
    endtask
    
    // Test patterns
    initial begin
        // Initialize
        inst = 48'h000000000000;
        valid = 1'b0;
        
        // Generate waveform dump
        $dumpfile("v60_decoder_tb.vcd");
        $dumpvars(0, v60_decoder_tb);
        
        $display("=== V60 Instruction Decoder Testbench ===");
        $display("Testing instruction formats per µPD70616 manual");
        
        // Test Format I instructions (single byte)
        display_decode("NOP (Format I)", 48'h900000000000);
        display_decode("HLT (Format I)", 48'hF40000000000);
        
        // Test Format II instructions (two bytes)
        display_decode("PUSH R0 (Format II)", 48'h500000000000);
        display_decode("PUSH R7 (Format II)", 48'h570000000000);
        display_decode("POP R0 (Format II)", 48'h580000000000);
        display_decode("POP R7 (Format II)", 48'h5F0000000000);
        
        // Test Format III instructions (with immediate)
        display_decode("MOV R0, #0x1234 (Format III)", 48'hB834120000000);
        display_decode("MOV R15, #0x5678 (Format III)", 48'hBF78560000000);
        display_decode("JMP rel8 (Format III)", 48'hEB10000000000);
        display_decode("JMP rel32 (Format III)", 48'hE912345678000);
        
        // Test Format V instructions (two operands)
        display_decode("MOV r/m, r (Format V)", 48'h8800000000000);
        display_decode("MOV r, r/m (Format V)", 48'h8A00000000000);
        display_decode("ADD r/m, r (Format V)", 48'h0000000000000);
        display_decode("ADD r, r/m (Format V)", 48'h0200000000000);
        display_decode("SUB r/m, r (Format V)", 48'h2800000000000);
        
        // Test conditional jumps
        display_decode("JZ rel8 (Format III)", 48'h7410000000000);
        display_decode("JNZ rel8 (Format III)", 48'h7510000000000);
        display_decode("JC rel8 (Format III)", 48'h7210000000000);
        display_decode("JNC rel8 (Format III)", 48'h7310000000000);
        
        // Test invalid instruction
        display_decode("Invalid Instruction", 48'hFF0000000000);
        
        // Verify 32-register capability
        $display("\n--- Register Range Verification ---");
        
        // Test with register numbers that would exceed 4-bit range
        inst = 48'hB834120000000;  // MOV R0, immediate (should work)
        valid = 1'b1;
        #1;
        if (dst_reg > 31) begin
            $error("FAIL: Register number exceeds V60 range");
        end else begin
            $display("PASS: Register decoding within valid range");
        end
        
        // Test edge cases
        $display("\n--- Edge Case Tests ---");
        
        // Test with valid=0
        valid = 1'b0;
        #1;
        if (!illegal) begin
            $error("FAIL: Should be illegal when valid=0");
        end else begin
            $display("PASS: Correctly flags illegal when valid=0");
        end
        
        // Test length calculations
        $display("\n--- Instruction Length Verification ---");
        
        // Single byte instructions
        display_decode("NOP length check", 48'h900000000000);
        if (inst_length != 1) begin
            $error("FAIL: NOP should be 1 byte, got %0d", inst_length);
        end else begin
            $display("PASS: NOP instruction length = 1 byte");
        end
        
        // Multi-byte instructions  
        display_decode("MOV R0,imm32 length check", 48'hB834120000000);
        if (inst_length != 5) begin
            $error("FAIL: MOV R,imm32 should be 5 bytes, got %0d", inst_length);
        end else begin
            $display("PASS: MOV R,imm32 instruction length = 5 bytes");
        end
        
        $display("\n=== Decoder Test Complete ===");
        $display("This testbench verifies V60 instruction format decoding");
        $display("per µPD70616 Programmer's Reference Manual");
        
        #50;
        $finish;
    end

endmodule

v60_decoder_tb.vcd
$date
	Tue Jul 29 11:14:44 2025
$end
$version
	Icarus Verilog
$end
$timescale
	1ps
$end
$scope module v60_decoder_tb $end
$var wire 1 ! uses_memory $end
$var wire 5 " src_reg [4:0] $end
$var wire 8 # opcode [7:0] $end
$var wire 3 $ inst_length [2:0] $end
$var wire 32 % immediate [31:0] $end
$var wire 1 & illegal $end
$var wire 3 ' format [2:0] $end
$var wire 5 ( dst_reg [4:0] $end
$var wire 2 ) data_type [1:0] $end
$var reg 48 * inst [47:0] $end
$var reg 1 + valid $end
$scope module dut $end
$var wire 48 , inst [47:0] $end
$var wire 1 + valid $end
$var wire 8 - opcode_byte [7:0] $end
$var reg 2 . data_type [1:0] $end
$var reg 2 / displacement_size [1:0] $end
$var reg 5 0 dst_reg [4:0] $end
$var reg 3 1 format [2:0] $end
$var reg 1 2 has_modrm $end
$var reg 1 3 has_sib $end
$var reg 1 & illegal $end
$var reg 32 4 immediate [31:0] $end
$var reg 2 5 immediate_size [1:0] $end
$var reg 3 6 inst_length [2:0] $end
$var reg 8 7 opcode [7:0] $end
$var reg 5 8 src_reg [4:0] $end
$var reg 1 ! uses_memory $end
$scope begin $unm_blk_18 $end
$var reg 2 9 mod_field [1:0] $end
$var reg 8 : modrm [7:0] $end
$var reg 3 ; reg_field [2:0] $end
$var reg 3 < rm_field [2:0] $end
$upscope $end
$upscope $end
$scope task display_decode $end
$var reg 48 = test_inst [47:0] $end
$upscope $end
$upscope $end
$enddefinitions $end
#0
$dumpvars
b100100000000000000000000000000000000000000000000 =
bx <
bx ;
bx :
bx 9
b0 8
b10010000 7
b1 6
b0 5
b0 4
03
02
b0 1
b0 0
b0 /
b10 .
b10010000 -
b100100000000000000000000000000000000000000000000 ,
1+
b100100000000000000000000000000000000000000000000 *
b10 )
b0 (
b0 '
0&
b0 %
b1 $
b10010000 #
b0 "
0!
$end
#1000
b11110100 #
b11110100 7
b11110100 -
b111101000000000000000000000000000000000000000000 *
b111101000000000000000000000000000000000000000000 ,
b111101000000000000000000000000000000000000000000 =
#2000
1!
b1 '
b1 1
b1010000 #
b1010000 7
b1010000 -
b10100000000000000000000000000000000000000000000 *
b10100000000000000000000000000000000000000000000 ,
b10100000000000000000000000000000000000000000000 =
#3000
b111 "
b111 8
1!
b1 '
b1 1
b1010111 #
b1010111 7
b1010111 -
b10101110000000000000000000000000000000000000000 *
b10101110000000000000000000000000000000000000000 ,
b10101110000000000000000000000000000000000000000 =
#4000
1!
b0 "
b0 8
b1 '
b1 1
b1011000 #
b1011000 7
b1011000 -
b10110000000000000000000000000000000000000000000 *
b10110000000000000000000000000000000000000000000 ,
b10110000000000000000000000000000000000000000000 =
#5000
b111 (
b111 0
1!
b1 '
b1 1
b1011111 #
b1011111 7
b1011111 -
b10111110000000000000000000000000000000000000000 *
b10111110000000000000000000000000000000000000000 ,
b10111110000000000000000000000000000000000000000 =
#6000
b100000 %
b100000 4
1&
0!
b0 (
b0 0
b0 '
b0 1
b10000011 #
b10000011 7
b10000011 -
b100000110100000100100000000000000000000000000000 *
b100000110100000100100000000000000000000000000000 ,
b100000110100000100100000000000000000000000000000 =
#7000
1&
b1100000 %
b1100000 4
b11110111 #
b11110111 7
b11110111 -
b111101111000010101100000000000000000000000000000 *
b111101111000010101100000000000000000000000000000 ,
b111101111000010101100000000000000000000000000000 =
#8000
b10 $
b10 6
b0 )
b0 .
b1 (
b1 0
b10 '
b10 1
0&
b0 %
b0 4
b10110001 #
b10110001 7
b10110001 -
b101100010000000000000000000000000000000000000000 *
b101100010000000000000000000000000000000000000000 ,
b101100010000000000000000000000000000000000000000 =
#9000
b1000101 %
b1000101 4
1&
b1 $
b1 6
b0 (
b0 0
b10 )
b10 .
b0 '
b0 1
b10010001 #
b10010001 7
b10010001 -
b100100010010001101000101011001111000000000000000 *
b100100010010001101000101011001111000000000000000 ,
b100100010010001101000101011001111000000000000000 =
#10000
1&
b0 %
b0 4
b10000000 #
b10000000 7
b10000000 -
b100000000000000000000000000000000000000000000000 *
b100000000000000000000000000000000000000000000000 ,
b100000000000000000000000000000000000000000000000 =
#11000
1&
b10100000 #
b10100000 7
b10100000 -
b101000000000000000000000000000000000000000000000 *
b101000000000000000000000000000000000000000000000 ,
b101000000000000000000000000000000000000000000000 =
#12000
b10 $
b10 6
12
b0 )
b0 .
b100 '
b100 1
0&
b0 #
b0 7
b0 -
b0 *
b0 ,
b0 =
#13000
1&
02
b1 $
b1 6
b10 )
b10 .
b0 '
b0 1
b100000 #
b100000 7
b100000 -
b1000000000000000000000000000000000000000000000 *
b1000000000000000000000000000000000000000000000 ,
b1000000000000000000000000000000000000000000000 =
#14000
1&
b10000000 #
b10000000 7
b10000000 -
b100000000000000000000000000000000000000000000000 *
b100000000000000000000000000000000000000000000000 ,
b100000000000000000000000000000000000000000000000 =
#15000
1&
b1000001 #
b1000001 7
b1000001 -
b10000010000000000000000000000000000000000000000 *
b10000010000000000000000000000000000000000000000 ,
b10000010000000000000000000000000000000000000000 =
#16000
1!
b1 "
b1 8
b1 '
b1 1
0&
b1010001 #
b1010001 7
b1010001 -
b10100010000000000000000000000000000000000000000 *
b10100010000000000000000000000000000000000000000 ,
b10100010000000000000000000000000000000000000000 =
#17000
1&
0!
b0 "
b0 8
b0 '
b0 1
b100001 #
b100001 7
b100001 -
b1000010000000000000000000000000000000000000000 *
b1000010000000000000000000000000000000000000000 ,
b1000010000000000000000000000000000000000000000 =
#18000
1&
b110001 #
b110001 7
b110001 -
b1100010000000000000000000000000000000000000000 *
b1100010000000000000000000000000000000000000000 ,
b1100010000000000000000000000000000000000000000 =
#19000
1&
b11111111 #
b11111111 7
b11111111 -
b111111110000000000000000000000000000000000000000 *
b111111110000000000000000000000000000000000000000 ,
b111111110000000000000000000000000000000000000000 =
#20000
b100000 %
b100000 4
1&
b10000011 #
b10000011 7
b10000011 -
b100000110100000100100000000000000000000000000000 *
b100000110100000100100000000000000000000000000000 ,
#21000
1&
b0 %
b0 4
0+
#22000
0&
b10010000 #
b10010000 7
b10010000 -
1+
b100100000000000000000000000000000000000000000000 *
b100100000000000000000000000000000000000000000000 ,
b100100000000000000000000000000000000000000000000 =
#23000
b100000 %
b100000 4
1&
b10000011 #
b10000011 7
b10000011 -
b100000110100000100100000000000000000000000000000 *
b100000110100000100100000000000000000000000000000 ,
b100000110100000100100000000000000000000000000000 =
