rtl/core/v60_defines.sv
`ifndef V60_DEFINES_SV
`define V60_DEFINES_SV

// V60 Architecture Constants
`define V60_DATA_WIDTH      32
`define V60_ADDR_WIDTH      32
`define V60_REG_WIDTH       32
`define V60_NUM_REGS        32

// General Purpose Registers (R0-R31)
`define V60_REG_R0          5'd0
`define V60_REG_R1          5'd1
`define V60_REG_R2          5'd2
`define V60_REG_R3          5'd3
`define V60_REG_R4          5'd4
`define V60_REG_R5          5'd5
`define V60_REG_R6          5'd6
`define V60_REG_R7          5'd7
`define V60_REG_R8          5'd8
`define V60_REG_R9          5'd9
`define V60_REG_R10         5'd10
`define V60_REG_R11         5'd11
`define V60_REG_R12         5'd12
`define V60_REG_R13         5'd13
`define V60_REG_R14         5'd14
`define V60_REG_R15         5'd15
`define V60_REG_R16         5'd16
`define V60_REG_R17         5'd17
`define V60_REG_R18         5'd18
`define V60_REG_R19         5'd19
`define V60_REG_R20         5'd20
`define V60_REG_R21         5'd21
`define V60_REG_R22         5'd22
`define V60_REG_R23         5'd23
`define V60_REG_R24         5'd24
`define V60_REG_R25         5'd25
`define V60_REG_R26         5'd26
`define V60_REG_R27         5'd27
`define V60_REG_R28         5'd28
`define V60_REG_R29         5'd29
`define V60_REG_R30         5'd30
`define V60_REG_R31         5'd31

// Special Purpose Registers (implicitly selected by instructions)
`define V60_REG_AP          5'd29   // Argument Pointer (R29)
`define V60_REG_FP          5'd30   // Frame Pointer (R30)
`define V60_REG_SP          5'd31   // Stack Pointer (R31)

// Program Status Word (PSW) bits
`define V60_PSW_V           0   // Overflow
`define V60_PSW_C           1   // Carry
`define V60_PSW_Z           2   // Zero
`define V60_PSW_S           3   // Sign
`define V60_PSW_TB          4   // Trap on Branch
`define V60_PSW_TP          5   // Trap Pending
`define V60_PSW_FPT         6   // Floating Point Trap
`define V60_PSW_PRNG        9:7 // Privilege Ring (0-7)
`define V60_PSW_IS          10  // Interrupt State
`define V60_PSW_FUD         11  // FPU Disable
`define V60_PSW_AT          12  // Address Translation
`define V60_PSW_DB          13  // Debug
`define V60_PSW_IM          14  // Interrupt Mask
`define V60_PSW_I           15  // Interrupt Enable

// Instruction Format Types (from V60 manual)
`define V60_FMT_I           3'd0   // Format I: One-byte instructions
`define V60_FMT_II          3'd1   // Format II: Two-byte instructions
`define V60_FMT_III         3'd2   // Format III: Instructions with immediate
`define V60_FMT_IV          3'd3   // Format IV: Instructions with displacement
`define V60_FMT_V           3'd4   // Format V: Two-operand instructions
`define V60_FMT_VI          3'd5   // Format VI: Three-operand instructions
`define V60_FMT_VII         3'd6   // Format VII: Special format instructions
`define V60_FMT_RESERVED    3'd7   // Reserved format

// Data Types
`define V60_TYPE_BYTE       2'd0   // 8-bit
`define V60_TYPE_HALFWORD   2'd1   // 16-bit
`define V60_TYPE_WORD       2'd2   // 32-bit
`define V60_TYPE_EXTENDED   2'd3   // 64-bit (FPU)

// Addressing Modes
`define V60_AM_REGISTER     3'd0   // Register direct
`define V60_AM_IMMEDIATE    3'd1   // Immediate
`define V60_AM_MEMORY       3'd2   // Memory direct
`define V60_AM_INDEXED      3'd3   // Register indirect with index
`define V60_AM_AUTOINCR     3'd4   // Auto-increment
`define V60_AM_AUTODECR     3'd5   // Auto-decrement
`define V60_AM_DISPLACED    3'd6   // Register indirect with displacement
`define V60_AM_PCRELATIVE   3'd7   // PC-relative

// Memory Access Types
`define V60_MEM_IDLE        2'd0
`define V60_MEM_READ        2'd1
`define V60_MEM_WRITE       2'd2
`define V60_MEM_RMW         2'd3   // Read-Modify-Write

// Exception Vectors
`define V60_VEC_RESET       8'h00
`define V60_VEC_NMI         8'h01
`define V60_VEC_INVALID_OP  8'h06
`define V60_VEC_DIV_ZERO    8'h07
`define V60_VEC_OVERFLOW    8'h08
`define V60_VEC_BOUNDS      8'h09
`define V60_VEC_DEBUG       8'h0D
`define V60_VEC_PAGE_FAULT  8'h0E
`define V60_VEC_ALIGNMENT   8'h11

`endif // V60_DEFINES_SV

rtl/core/v60_regfile.sv
`include "v60_defines.sv"

module v60_regfile (
    input  logic                       clk,
    input  logic                       rst_n,
    
    // Read port 1
    input  logic [4:0]                 raddr1,
    output logic [`V60_REG_WIDTH-1:0]  rdata1,
    
    // Read port 2
    input  logic [4:0]                 raddr2,
    output logic [`V60_REG_WIDTH-1:0]  rdata2,
    
    // Write port
    input  logic [4:0]                 waddr,
    input  logic [`V60_REG_WIDTH-1:0]  wdata,
    input  logic                       wen
);

    // Register file storage
    logic [`V60_REG_WIDTH-1:0] registers [0:`V60_NUM_REGS-1];
    
    // Read operations (combinational)
    always_comb begin
        rdata1 = registers[raddr1];
        rdata2 = registers[raddr2];
    end
    
    // Write operation (sequential)
    always_ff @(posedge clk or negedge rst_n) begin
        if (!rst_n) begin
            // Initialize all registers to 0
            for (int i = 0; i < `V60_NUM_REGS; i++) begin
                registers[i] <= 32'h0000_0000;
            end
        end else begin
            if (wen) begin
                registers[waddr] <= wdata;
            end
        end
    end
    
    // Synthesis optimization attributes
    // synthesis syn_ramstyle = "registers"
    // synthesis syn_keep = 1

endmodule

tb/v60_regfile_tb.sv
`timescale 1ns/1ps
`include "v60_defines.sv"

module v60_regfile_tb;

    // Clock and reset
    logic clk;
    logic rst_n;
    
    // Register file signals
    logic [4:0]                 raddr1;
    logic [`V60_REG_WIDTH-1:0]  rdata1;
    logic [4:0]                 raddr2;
    logic [`V60_REG_WIDTH-1:0]  rdata2;
    logic [4:0]                 waddr;
    logic [`V60_REG_WIDTH-1:0]  wdata;
    logic                       wen;
    
    // DUT instantiation
    v60_regfile dut (
        .clk        (clk),
        .rst_n      (rst_n),
        .raddr1     (raddr1),
        .rdata1     (rdata1),
        .raddr2     (raddr2),
        .rdata2     (rdata2),
        .waddr      (waddr),
        .wdata      (wdata),
        .wen        (wen)
    );
    
    // Clock generation
    initial begin
        clk = 0;
        forever #5 clk = ~clk;  // 100MHz clock
    end
    
    // Test patterns
    initial begin
        // Initialize signals
        rst_n = 0;
        raddr1 = 5'h00;
        raddr2 = 5'h00;
        waddr = 5'h00;
        wdata = 32'h00000000;
        wen = 1'b0;
        
        // Generate waveform dump
        $dumpfile("v60_regfile_tb.vcd");
        $dumpvars(0, v60_regfile_tb);
        
        // Reset sequence
        #20 rst_n = 1;
        #10;
        
        $display("=== V60 Register File Testbench ===");
        $display("Testing 32-register implementation per V60 manual");
        
        // Test 1: Verify all registers reset to 0
        $display("\n--- Test 1: Reset state verification ---");
        for (int i = 0; i < 32; i++) begin
            raddr1 = i;
            #1;  // Allow combinational delay
            if (rdata1 !== 32'h00000000) begin
                $error("FAIL: Register R%0d not reset to 0, got 0x%08x", i, rdata1);
            end else begin
                $display("PASS: Register R%0d = 0x%08x", i, rdata1);
            end
        end
        
        // Test 2: Write to all registers
        $display("\n--- Test 2: Write test to all 32 registers ---");
        for (int i = 0; i < 32; i++) begin
            @(posedge clk);
            waddr = i;
            wdata = 32'hA5A5A5A5 + i;  // Unique pattern per register
            wen = 1'b1;
            @(posedge clk);
            wen = 1'b0;
            
            // Verify write
            raddr1 = i;
            #1;
            if (rdata1 !== (32'hA5A5A5A5 + i)) begin
                $error("FAIL: Register R%0d write failed, expected 0x%08x, got 0x%08x", 
                       i, 32'hA5A5A5A5 + i, rdata1);
            end else begin
                $display("PASS: Register R%0d = 0x%08x", i, rdata1);
            end
        end
        
        // Test 3: Dual-port read test
        $display("\n--- Test 3: Dual-port read test ---");
        for (int i = 0; i < 16; i++) begin
            raddr1 = i;
            raddr2 = 31-i;
            #1;
            $display("Port1: R%0d = 0x%08x, Port2: R%0d = 0x%08x", 
                     i, rdata1, 31-i, rdata2);
            
            if (rdata1 !== (32'hA5A5A5A5 + i)) begin
                $error("FAIL: Port1 read R%0d failed", i);
            end
            if (rdata2 !== (32'hA5A5A5A5 + (31-i))) begin
                $error("FAIL: Port2 read R%0d failed", 31-i);
            end
        end
        
        // Test 4: Special register aliases (AP, FP, SP)
        $display("\n--- Test 4: Special register verification ---");
        
        // Test AP (R29)
        raddr1 = `V60_REG_AP;
        #1;
        $display("AP (R29) = 0x%08x", rdata1);
        if (rdata1 !== (32'hA5A5A5A5 + 29)) begin
            $error("FAIL: AP register access failed");
        end
        
        // Test FP (R30)
        raddr1 = `V60_REG_FP;
        #1;
        $display("FP (R30) = 0x%08x", rdata1);
        if (rdata1 !== (32'hA5A5A5A5 + 30)) begin
            $error("FAIL: FP register access failed");
        end
        
        // Test SP (R31)
        raddr1 = `V60_REG_SP;
        #1;
        $display("SP (R31) = 0x%08x", rdata1);
        if (rdata1 !== (32'hA5A5A5A5 + 31)) begin
            $error("FAIL: SP register access failed");
        end
        
        // Test 5: Write enable functionality
        $display("\n--- Test 5: Write enable test ---");
        @(posedge clk);
        waddr = 5'd15;
        wdata = 32'hDEADBEEF;
        wen = 1'b0;  // Write disabled
        @(posedge clk);
        
        raddr1 = 5'd15;
        #1;
        if (rdata1 === 32'hDEADBEEF) begin
            $error("FAIL: Write occurred when wen=0");
        end else begin
            $display("PASS: Write correctly disabled when wen=0");
        end
        
        // Test 6: Boundary conditions
        $display("\n--- Test 6: Boundary condition tests ---");
        
        // Test register 0
        @(posedge clk);
        waddr = 5'd0;
        wdata = 32'h12345678;
        wen = 1'b1;
        @(posedge clk);
        wen = 1'b0;
        
        raddr1 = 5'd0;
        #1;
        if (rdata1 !== 32'h12345678) begin
            $error("FAIL: Register 0 boundary test failed");
        end else begin
            $display("PASS: Register 0 boundary test passed");
        end
        
        // Test register 31 (highest)
        @(posedge clk);
        waddr = 5'd31;
        wdata = 32'h87654321;
        wen = 1'b1;
        @(posedge clk);
        wen = 1'b0;
        
        raddr1 = 5'd31;
        #1;
        if (rdata1 !== 32'h87654321) begin
            $error("FAIL: Register 31 boundary test failed");
        end else begin
            $display("PASS: Register 31 boundary test passed");
        end
        
        $display("\n=== Register File Test Complete ===");
        $display("This testbench verifies the V60 register file has 32 registers");
        $display("as specified in the µPD70616 Programmer's Reference Manual");
        
        #50;
        $finish;
    end

endmodule

v60_regfile_tb.vcd
$date
	Tue Jul 29 11:14:22 2025
$end
$version
	Icarus Verilog
$end
$timescale
	1ps
$end
$scope module v60_regfile_tb $end
$var wire 32 ! rdata2 [31:0] $end
$var wire 32 " rdata1 [31:0] $end
$var reg 1 # clk $end
$var reg 5 $ raddr1 [4:0] $end
$var reg 5 % raddr2 [4:0] $end
$var reg 1 & rst_n $end
$var reg 5 ' waddr [4:0] $end
$var reg 32 ( wdata [31:0] $end
$var reg 1 ) wen $end
$scope module dut $end
$var wire 1 # clk $end
$var wire 5 * raddr1 [4:0] $end
$var wire 5 + raddr2 [4:0] $end
$var wire 1 & rst_n $end
$var wire 5 , waddr [4:0] $end
$var wire 32 - wdata [31:0] $end
$var wire 1 ) wen $end
$var reg 32 . rdata1 [31:0] $end
$var reg 32 / rdata2 [31:0] $end
$scope begin $ivl_for_loop0 $end
$var integer 32 0 i [31:0] $end
$upscope $end
$upscope $end
$scope begin $ivl_for_loop1 $end
$var integer 32 1 i [31:0] $end
$upscope $end
$scope begin $ivl_for_loop2 $end
$var integer 32 2 i [31:0] $end
$upscope $end
$scope begin $ivl_for_loop3 $end
$var integer 32 3 i [31:0] $end
$upscope $end
$upscope $end
$enddefinitions $end
#0
$dumpvars
b0 3
b0 2
b0 1
b100000 0
b0 /
b0 .
b0 -
b0 ,
b0 +
b0 *
0)
b0 (
b0 '
0&
b0 %
b0 $
0#
b0 "
b0 !
$end
#5000
b100000 0
1#
#10000
0#
#15000
b100000 0
1#
#20000
0#
1&
#25000
1#
#30000
0#
#31000
b1 $
b1 *
b1 1
#32000
b10 $
b10 *
b10 1
#33000
b11 $
b11 *
b11 1
#34000
b100 $
b100 *
b100 1
#35000
b101 $
b101 *
b101 1
1#
#36000
b110 $
b110 *
b110 1
#37000
b111 $
b111 *
b111 1
#38000
b1000 $
b1000 *
b1000 1
#39000
b1001 $
b1001 *
b1001 1
#40000
b1010 $
b1010 *
b1010 1
0#
#41000
b1011 $
b1011 *
b1011 1
#42000
b1100 $
b1100 *
b1100 1
#43000
b1101 $
b1101 *
b1101 1
#44000
b1110 $
b1110 *
b1110 1
#45000
b1111 $
b1111 *
b1111 1
1#
#46000
b10000 $
b10000 *
b10000 1
#47000
b10001 $
b10001 *
b10001 1
#48000
b10010 $
b10010 *
b10010 1
#49000
b10011 $
b10011 *
b10011 1
#50000
b10100 $
b10100 *
b10100 1
0#
#51000
b10101 $
b10101 *
b10101 1
#52000
b10110 $
b10110 *
b10110 1
#53000
b10111 $
b10111 *
b10111 1
#54000
b11000 $
b11000 *
b11000 1
#55000
b11001 $
b11001 *
b11001 1
1#
#56000
b11010 $
b11010 *
b11010 1
#57000
b11011 $
b11011 *
b11011 1
#58000
b11100 $
b11100 *
b11100 1
#59000
b11101 $
b11101 *
b11101 1
#60000
b11110 $
b11110 *
b11110 1
0#
#61000
b11111 $
b11111 *
b11111 1
#62000
b100000 1
#65000
b10100101101001011010010110100101 !
b10100101101001011010010110100101 /
1)
b10100101101001011010010110100101 (
b10100101101001011010010110100101 -
1#
#70000
0#
#75000
b10100101101001011010010110100101 "
b10100101101001011010010110100101 .
b0 $
b0 *
0)
1#
#76000
b1 2
#80000
0#
#85000
1)
b10100101101001011010010110100110 (
b10100101101001011010010110100110 -
b1 '
b1 ,
1#
#90000
0#
#95000
b10100101101001011010010110100110 "
b10100101101001011010010110100110 .
b1 $
b1 *
0)
1#
#96000
b10 2
#100000
0#
#105000
1)
b10100101101001011010010110100111 (
b10100101101001011010010110100111 -
b10 '
b10 ,
1#
#110000
0#
#115000
b10100101101001011010010110100111 "
b10100101101001011010010110100111 .
b10 $
b10 *
0)
1#
#116000
b11 2
#120000
0#
#125000
1)
b10100101101001011010010110101000 (
b10100101101001011010010110101000 -
b11 '
b11 ,
1#
#130000
0#
#135000
b10100101101001011010010110101000 "
b10100101101001011010010110101000 .
b11 $
b11 *
0)
1#
#136000
b100 2
#140000
0#
#145000
1)
b10100101101001011010010110101001 (
b10100101101001011010010110101001 -
b100 '
b100 ,
1#
#150000
0#
#155000
b10100101101001011010010110101001 "
b10100101101001011010010110101001 .
b100 $
b100 *
0)
1#
#156000
b101 2
#160000
0#
#165000
1)
b10100101101001011010010110101010 (
b10100101101001011010010110101010 -
b101 '
b101 ,
1#
#170000
0#
#175000
b10100101101001011010010110101010 "
b10100101101001011010010110101010 .
b101 $
b101 *
0)
1#
#176000
b110 2
#180000
0#
#185000
1)
b10100101101001011010010110101011 (
b10100101101001011010010110101011 -
b110 '
b110 ,
1#
#190000
0#
#195000
b10100101101001011010010110101011 "
b10100101101001011010010110101011 .
b110 $
b110 *
0)
1#
#196000
b111 2
#200000
0#
#205000
1)
b10100101101001011010010110101100 (
b10100101101001011010010110101100 -
b111 '
b111 ,
1#
#210000
0#
#215000
b10100101101001011010010110101100 "
b10100101101001011010010110101100 .
b111 $
b111 *
0)
1#
#216000
b1000 2
#220000
0#
#225000
1)
b10100101101001011010010110101101 (
b10100101101001011010010110101101 -
b1000 '
b1000 ,
1#
#230000
0#
#235000
b10100101101001011010010110101101 "
b10100101101001011010010110101101 .
b1000 $
b1000 *
0)
1#
#236000
b1001 2
#240000
0#
#245000
1)
b10100101101001011010010110101110 (
b10100101101001011010010110101110 -
b1001 '
b1001 ,
1#
#250000
0#
#255000
b10100101101001011010010110101110 "
b10100101101001011010010110101110 .
b1001 $
b1001 *
0)
1#
#256000
b1010 2
#260000
0#
#265000
1)
b10100101101001011010010110101111 (
b10100101101001011010010110101111 -
b1010 '
b1010 ,
1#
#270000
0#
#275000
b10100101101001011010010110101111 "
b10100101101001011010010110101111 .
b1010 $
b1010 *
0)
1#
#276000
b1011 2
#280000
0#
#285000
1)
b10100101101001011010010110110000 (
b10100101101001011010010110110000 -
b1011 '
b1011 ,
1#
#290000
0#
#295000
b10100101101001011010010110110000 "
b10100101101001011010010110110000 .
b1011 $
b1011 *
0)
1#
#296000
b1100 2
#300000
0#
#305000
1)
b10100101101001011010010110110001 (
b10100101101001011010010110110001 -
b1100 '
b1100 ,
1#
#310000
0#
#315000
b10100101101001011010010110110001 "
b10100101101001011010010110110001 .
b1100 $
b1100 *
0)
1#
#316000
b1101 2
#320000
0#
#325000
1)
b10100101101001011010010110110010 (
b10100101101001011010010110110010 -
b1101 '
b1101 ,
1#
#330000
0#
#335000
b10100101101001011010010110110010 "
b10100101101001011010010110110010 .
b1101 $
b1101 *
0)
1#
#336000
b1110 2
#340000
0#
#345000
1)
b10100101101001011010010110110011 (
b10100101101001011010010110110011 -
b1110 '
b1110 ,
1#
#350000
0#
#355000
b10100101101001011010010110110011 "
b10100101101001011010010110110011 .
b1110 $
b1110 *
0)
1#
#356000
b1111 2
#360000
0#
#365000
1)
b10100101101001011010010110110100 (
b10100101101001011010010110110100 -
b1111 '
b1111 ,
1#
#370000
0#
#375000
b10100101101001011010010110110100 "
b10100101101001011010010110110100 .
b1111 $
b1111 *
0)
1#
#376000
b10000 2
#380000
0#
#385000
1)
b10100101101001011010010110110101 (
b10100101101001011010010110110101 -
b10000 '
b10000 ,
1#
#390000
0#
#395000
b10100101101001011010010110110101 "
b10100101101001011010010110110101 .
b10000 $
b10000 *
0)
1#
#396000
b10001 2
#400000
0#
#405000
1)
b10100101101001011010010110110110 (
b10100101101001011010010110110110 -
b10001 '
b10001 ,
1#
#410000
0#
#415000
b10100101101001011010010110110110 "
b10100101101001011010010110110110 .
b10001 $
b10001 *
0)
1#
#416000
b10010 2
#420000
0#
#425000
1)
b10100101101001011010010110110111 (
b10100101101001011010010110110111 -
b10010 '
b10010 ,
1#
#430000
0#
#435000
b10100101101001011010010110110111 "
b10100101101001011010010110110111 .
b10010 $
b10010 *
0)
1#
#436000
b10011 2
#440000
0#
#445000
1)
b10100101101001011010010110111000 (
b10100101101001011010010110111000 -
b10011 '
b10011 ,
1#
#450000
0#
#455000
b10100101101001011010010110111000 "
b10100101101001011010010110111000 .
b10011 $
b10011 *
0)
1#
#456000
b10100 2
#460000
0#
#465000
1)
b10100101101001011010010110111001 (
b10100101101001011010010110111001 -
b10100 '
b10100 ,
1#
#470000
0#
#475000
b10100101101001011010010110111001 "
b10100101101001011010010110111001 .
b10100 $
b10100 *
0)
1#
#476000
b10101 2
#480000
0#
#485000
1)
b10100101101001011010010110111010 (
b10100101101001011010010110111010 -
b10101 '
b10101 ,
1#
#490000
0#
#495000
b10100101101001011010010110111010 "
b10100101101001011010010110111010 .
b10101 $
b10101 *
0)
1#
#496000
b10110 2
#500000
0#
#505000
1)
b10100101101001011010010110111011 (
b10100101101001011010010110111011 -
b10110 '
b10110 ,
1#
#510000
0#
#515000
b10100101101001011010010110111011 "
b10100101101001011010010110111011 .
b10110 $
b10110 *
0)
1#
#516000
b10111 2
#520000
0#
#525000
1)
b10100101101001011010010110111100 (
b10100101101001011010010110111100 -
b10111 '
b10111 ,
1#
#530000
0#
#535000
b10100101101001011010010110111100 "
b10100101101001011010010110111100 .
b10111 $
b10111 *
0)
1#
#536000
b11000 2
#540000
0#
#545000
1)
b10100101101001011010010110111101 (
b10100101101001011010010110111101 -
b11000 '
b11000 ,
1#
#550000
0#
#555000
b10100101101001011010010110111101 "
b10100101101001011010010110111101 .
b11000 $
b11000 *
0)
1#
#556000
b11001 2
#560000
0#
#565000
1)
b10100101101001011010010110111110 (
b10100101101001011010010110111110 -
b11001 '
b11001 ,
1#
#570000
0#
#575000
b10100101101001011010010110111110 "
b10100101101001011010010110111110 .
b11001 $
b11001 *
0)
1#
#576000
b11010 2
#580000
0#
#585000
1)
b10100101101001011010010110111111 (
b10100101101001011010010110111111 -
b11010 '
b11010 ,
1#
#590000
0#
#595000
b10100101101001011010010110111111 "
b10100101101001011010010110111111 .
b11010 $
b11010 *
0)
1#
#596000
b11011 2
#600000
0#
#605000
1)
b10100101101001011010010111000000 (
b10100101101001011010010111000000 -
b11011 '
b11011 ,
1#
#610000
0#
#615000
b10100101101001011010010111000000 "
b10100101101001011010010111000000 .
b11011 $
b11011 *
0)
1#
#616000
b11100 2
#620000
0#
#625000
1)
b10100101101001011010010111000001 (
b10100101101001011010010111000001 -
b11100 '
b11100 ,
1#
#630000
0#
#635000
b10100101101001011010010111000001 "
b10100101101001011010010111000001 .
b11100 $
b11100 *
0)
1#
#636000
b11101 2
#640000
0#
#645000
1)
b10100101101001011010010111000010 (
b10100101101001011010010111000010 -
b11101 '
b11101 ,
1#
#650000
0#
#655000
b10100101101001011010010111000010 "
b10100101101001011010010111000010 .
b11101 $
b11101 *
0)
1#
#656000
b11110 2
#660000
0#
#665000
1)
b10100101101001011010010111000011 (
b10100101101001011010010111000011 -
b11110 '
b11110 ,
1#
#670000
0#
#675000
b10100101101001011010010111000011 "
b10100101101001011010010111000011 .
b11110 $
b11110 *
0)
1#
#676000
b11111 2
#680000
0#
#685000
1)
b10100101101001011010010111000100 (
b10100101101001011010010111000100 -
b11111 '
b11111 ,
1#
#690000
0#
#695000
b10100101101001011010010111000100 "
b10100101101001011010010111000100 .
b11111 $
b11111 *
0)
1#
#696000
b10100101101001011010010111000100 !
b10100101101001011010010111000100 /
b10100101101001011010010110100101 "
b10100101101001011010010110100101 .
b11111 %
b11111 +
b0 $
b0 *
b100000 2
#697000
b10100101101001011010010111000011 !
b10100101101001011010010111000011 /
b10100101101001011010010110100110 "
b10100101101001011010010110100110 .
b11110 %
b11110 +
b1 $
b1 *
b1 3
#698000
b10100101101001011010010111000010 !
b10100101101001011010010111000010 /
b10100101101001011010010110100111 "
b10100101101001011010010110100111 .
b11101 %
b11101 +
b10 $
b10 *
b10 3
#699000
b10100101101001011010010111000001 !
b10100101101001011010010111000001 /
b10100101101001011010010110101000 "
b10100101101001011010010110101000 .
b11100 %
b11100 +
b11 $
b11 *
b11 3
#700000
b10100101101001011010010111000000 !
b10100101101001011010010111000000 /
b10100101101001011010010110101001 "
b10100101101001011010010110101001 .
b11011 %
b11011 +
b100 $
b100 *
b100 3
0#
#701000
b10100101101001011010010110111111 !
b10100101101001011010010110111111 /
b10100101101001011010010110101010 "
b10100101101001011010010110101010 .
b11010 %
b11010 +
b101 $
b101 *
b101 3
#702000
b10100101101001011010010110111110 !
b10100101101001011010010110111110 /
b10100101101001011010010110101011 "
b10100101101001011010010110101011 .
b11001 %
b11001 +
b110 $
b110 *
b110 3
#703000
b10100101101001011010010110111101 !
b10100101101001011010010110111101 /
b10100101101001011010010110101100 "
b10100101101001011010010110101100 .
b11000 %
b11000 +
b111 $
b111 *
b111 3
#704000
b10100101101001011010010110111100 !
b10100101101001011010010110111100 /
b10100101101001011010010110101101 "
b10100101101001011010010110101101 .
b10111 %
b10111 +
b1000 $
b1000 *
b1000 3
#705000
b10100101101001011010010110111011 !
b10100101101001011010010110111011 /
b10100101101001011010010110101110 "
b10100101101001011010010110101110 .
b10110 %
b10110 +
b1001 $
b1001 *
b1001 3
1#
#706000
b10100101101001011010010110111010 !
b10100101101001011010010110111010 /
b10100101101001011010010110101111 "
b10100101101001011010010110101111 .
b10101 %
b10101 +
b1010 $
b1010 *
b1010 3
#707000
b10100101101001011010010110111001 !
b10100101101001011010010110111001 /
b10100101101001011010010110110000 "
b10100101101001011010010110110000 .
b10100 %
b10100 +
b1011 $
b1011 *
b1011 3
#708000
b10100101101001011010010110111000 !
b10100101101001011010010110111000 /
b10100101101001011010010110110001 "
b10100101101001011010010110110001 .
b10011 %
b10011 +
b1100 $
b1100 *
b1100 3
#709000
b10100101101001011010010110110111 !
b10100101101001011010010110110111 /
b10100101101001011010010110110010 "
b10100101101001011010010110110010 .
b10010 %
b10010 +
b1101 $
b1101 *
b1101 3
#710000
b10100101101001011010010110110110 !
b10100101101001011010010110110110 /
b10100101101001011010010110110011 "
b10100101101001011010010110110011 .
b10001 %
b10001 +
b1110 $
b1110 *
b1110 3
0#
#711000
b10100101101001011010010110110101 !
b10100101101001011010010110110101 /
b10100101101001011010010110110100 "
b10100101101001011010010110110100 .
b10000 %
b10000 +
b1111 $
b1111 *
b1111 3
#712000
b10100101101001011010010111000010 "
b10100101101001011010010111000010 .
b11101 $
b11101 *
b10000 3
#713000
b10100101101001011010010111000011 "
b10100101101001011010010111000011 .
b11110 $
b11110 *
#714000
b10100101101001011010010111000100 "
b10100101101001011010010111000100 .
b11111 $
b11111 *
#715000
1#
#720000
0#
#725000
b11011110101011011011111011101111 (
b11011110101011011011111011101111 -
b1111 '
b1111 ,
1#
#730000
0#
#735000
b10100101101001011010010110110100 "
b10100101101001011010010110110100 .
b1111 $
b1111 *
1#
#740000
0#
#745000
1)
b10010001101000101011001111000 (
b10010001101000101011001111000 -
b0 '
b0 ,
1#
#750000
0#
#755000
b10010001101000101011001111000 "
b10010001101000101011001111000 .
b0 $
b0 *
0)
1#
#760000
0#
#765000
1)
b10000111011001010100001100100001 (
b10000111011001010100001100100001 -
b11111 '
b11111 ,
1#
#770000
0#
#775000
b10000111011001010100001100100001 "
b10000111011001010100001100100001 .
b11111 $
b11111 *
0)
1#
